{
  "timestamp": "2025-03-18T21:27:24.363Z",
  "endpoint": "crossCheck",
  "response": "1. Heavy menstrual bleeding and pelvic pain:\n- The patient, a 22-year-old female with a BMI of 40, presents with heavy menstrual bleeding and pelvic pain. Examination reveals an enlarged uterus, suggestive of fibroids. Further evaluation with ultrasound is recommended to confirm the diagnosis. Treatment options include medication for bleeding control or surgical intervention like myomectomy. Addressing PCOS is crucial for menstrual cycle regulation. Referral to a gynecologist for comprehensive management is advised.\n\n2. Possible diagnosis of fibroids:\n- Examination reveals an enlarged uterus, suggestive of fibroids. Further evaluation with ultrasound is recommended to confirm the diagnosis. Treatment options include medication for bleeding control or surgical intervention like myomectomy.\n\n3. PCOS management and menstrual cycle regulation:\n- Addressing PCOS is crucial for menstrual cycle regulation.\n\nHTML-formatted clinical note with adjustments based on guidelines:\n\n```html\n<p><strong>Summary:</strong>- Female, 22 years old, BMI 40, <i>heavy menstrual bleeding, pelvic pain</i>- Two prior pregnancies with cesarean sections- History of PCOS, appendectomy</p>\n\n<p><strong>Assessment and Advice:</strong>The patient, a 22-year-old female with a BMI of 40, presents with <i>heavy menstrual bleeding and pelvic pain</i>. Examination reveals an enlarged uterus, suggestive of fibroids. Further evaluation with ultrasound is recommended to confirm the diagnosis. Treatment options include medication for bleeding control or surgical intervention like myomectomy. Addressing PCOS is crucial for menstrual cycle regulation. Referral to a gynecologist for comprehensive management is advised.</p>\n\n<p><strong>Plan:</strong>1. Perform ultrasound to confirm fibroids.2. Initiate medication for bleeding control if indicated.3. Consider surgical intervention like myomectomy if needed.4. Address PCOS management for menstrual cycle regulation.5. Refer to a gynecologist for further evaluation and management.</p>\n```",
  "success": true,
  "error": "No error message"
}